richillcapital_line/__init__.py
richillcapital_line/clients.py
richillcapital_line/exceptions.py
richillcapital_line/models.py
richillcapital_line-0.1.1.dist-info/WHEEL
richillcapital_line-0.1.1.dist-info/METADATA
richillcapital_line-0.1.1.dist-info/RECORD
