Metadata-Version: 2.1
Name: richillcapital-line
Version: 0.1.1
License: MIT
Author-email: Mengsyue Amao Tsai <mengsyue.tsai@outlook.com>
Requires-Python: >=3.11
Requires-Dist: richillcapital-http>=0.1.1
